setup.py
perfomance_log.egg-info/PKG-INFO
perfomance_log.egg-info/SOURCES.txt
perfomance_log.egg-info/dependency_links.txt
perfomance_log.egg-info/not-zip-safe
perfomance_log.egg-info/requires.txt
perfomance_log.egg-info/top_level.txt
perfomance_logging/__init__.py
perfomance_logging/logging.py