Metadata-Version: 1.0
Name: perfomance-log
Version: 1.0.1
Summary: Perfomance logging
Home-page: UNKNOWN
Author: Alex Yung
Author-email: UNKNOWN
License: UNKNOWN
Platform: UNKNOWN
